atk_training_pritam_oop_wf_basic/BasicStreamFunctionRepository.py
atk_training_pritam_oop_wf_basic/Processor.py
atk_training_pritam_oop_wf_basic/StreamFunctionRepository.py
atk_training_pritam_oop_wf_basic/__init__.py
atk_training_pritam_oop_wf_basic/base_clases.py
atk_training_pritam_oop_wf_basic/commands.py
atk_training_pritam_oop_wf_basic/file_operations.py
atk_training_pritam_oop_wf_basic/processing_functions.py
atk_training_pritam_oop_wf_basic-0.1.0.dist-info/METADATA
atk_training_pritam_oop_wf_basic-0.1.0.dist-info/WHEEL
atk_training_pritam_oop_wf_basic-0.1.0.dist-info/entry_points.txt
atk_training_pritam_oop_wf_basic-0.1.0.dist-info/RECORD
