Metadata-Version: 2.1
Name: atk-training-pritam-oop-wf-basic
Version: 0.1.0
Summary: Framework for training wf projects using classes and objects
Author: Pritam Chowdhury
Author-email: pritam@aganitha.ai
Requires-Python: >=3.11,<4.0
Classifier: Programming Language :: Python :: 3
Classifier: Programming Language :: Python :: 3.11
Classifier: Programming Language :: Python :: 3.12
Requires-Dist: pyyaml (>=6.0.1,<7.0.0)
Requires-Dist: requests (>=2.31.0,<3.0.0)
Requires-Dist: typer (>=0.9.0,<0.10.0)
